[
  {"result_id": "215fc1f6-2a40-45d8-be2e-802e9c6c58dc", "crivo_dev_id": 287, "crivo_class_id": 16, "crivo_num_id": 16},
  {"result_id": "624995db-55f3-4244-b5a1-7f5a9a6dda4b", "crivo_dev_id": 288, "crivo_class_id": 17, "crivo_num_id": 17},
  {"result_id": "23ace4d9-7eae-4eb7-89b4-f2965645f7ad", "crivo_dev_id": 289, "crivo_class_id": 6, "crivo_num_id": null},
  {"result_id": "e028544e-e6a8-46e6-9c15-eef2ab1b1718", "crivo_dev_id": 290, "crivo_class_id": 31, "crivo_num_id": 31},
  {"result_id": "6c996536-8928-4772-9f07-1c412dd62be9", "crivo_dev_id": 291, "crivo_class_id": 26, "crivo_num_id": 26},
  {"result_id": "648a8e14-0467-4efd-a064-9ccf1a5bdbde", "crivo_dev_id": 292, "crivo_class_id": null, "crivo_num_id": 6},
  {"result_id": "34f41342-f911-42ab-be78-37c4d560b73d", "crivo_dev_id": 293, "crivo_class_id": 29, "crivo_num_id": 29},
  {"result_id": "85104078-d0ec-4e5f-b9c2-d8d7be3ce65c", "crivo_dev_id": 294, "crivo_class_id": null, "crivo_num_id": 4},
  {"result_id": "c47c5ee6-363e-4b62-92b3-f5c455a97088", "crivo_dev_id": 295, "crivo_class_id": 25, "crivo_num_id": 25},
  {"result_id": "7bc2191c-8968-4979-9837-64088bb3916c", "crivo_dev_id": 296, "crivo_class_id": 28, "crivo_num_id": 28},
  {"result_id": "6c14f1e5-6924-45b3-9d52-faea4fcfc4d6", "crivo_dev_id": 297, "crivo_class_id": 18, "crivo_num_id": null},
  {"result_id": "7c42e6a9-408a-4933-a157-7ae61c95bc6f", "crivo_dev_id": 298, "crivo_class_id": 4, "crivo_num_id": 18},
  {"result_id": "29a1d5ed-17ce-42b7-b79d-796e0689fe57", "crivo_dev_id": 299, "crivo_class_id": 13, "crivo_num_id": 13},
  {"result_id": "7fb2be73-3a02-4446-acff-5c5bc193c85b", "crivo_dev_id": 300, "crivo_class_id": null, "crivo_num_id": 7},
  {"result_id": "609ad910-d8e2-4b4d-b801-89fd6385de60", "crivo_dev_id": 301, "crivo_class_id": 20, "crivo_num_id": 20},
  {"result_id": "3e9bd971-0faa-4eb3-89cd-2b97946b6ff9", "crivo_dev_id": 302, "crivo_class_id": 8, "crivo_num_id": 2},
  {"result_id": "1621ec01-a254-4493-8264-26e798973521", "crivo_dev_id": 303, "crivo_class_id": 27, "crivo_num_id": 27},
  {"result_id": "61efe578-2bf3-47d3-90e4-a7602bdc5818", "crivo_dev_id": 304, "crivo_class_id": 21, "crivo_num_id": 21},
  {"result_id": "ee3f5b38-4061-4c67-8922-27da68128383", "crivo_dev_id": 305, "crivo_class_id": null, "crivo_num_id": 3},
  {"result_id": "981cc5fb-a90e-4b0d-9d37-db6dc675e4f2", "crivo_dev_id": 306, "crivo_class_id": 11, "crivo_num_id": 11},
  {"result_id": "87bd2d86-c44f-4f82-aab5-42c38d1c1cdd", "crivo_dev_id": 307, "crivo_class_id": 10, "crivo_num_id": 30},
  {"result_id": "8ce151b2-a6ce-4067-812c-764e1c0dec50", "crivo_dev_id": 308, "crivo_class_id": 30, "crivo_num_id": null},
  {"result_id": "b6365da7-b0f2-489b-9ce7-0cdf9f64bd98", "crivo_dev_id": 309, "crivo_class_id": 23, "crivo_num_id": 23},
  {"result_id": "4c22fd1e-a9d7-4e29-bb69-c2a68a41e165", "crivo_dev_id": 310, "crivo_class_id": 3, "crivo_num_id": null},
  {"result_id": "8ac57965-0563-43f0-ae3d-34426bb5a7af", "crivo_dev_id": 311, "crivo_class_id": null, "crivo_num_id": 8},
  {"result_id": "099eb090-4700-4294-a6df-274acfc8c8d9", "crivo_dev_id": 312, "crivo_class_id": 2, "crivo_num_id": null},
  {"result_id": "c7450671-4439-4ea1-93bb-2cb77dc21c93", "crivo_dev_id": 313, "crivo_class_id": null, "crivo_num_id": 1},
  {"result_id": "4e538536-9dec-47b2-b106-4e5a0ad10829", "crivo_dev_id": 314, "crivo_class_id": 22, "crivo_num_id": 22},
  {"result_id": "d7738139-3391-4aef-b17e-6cf7f463ff77", "crivo_dev_id": 315, "crivo_class_id": null, "crivo_num_id": 5},
  {"result_id": "2d81cdd4-ea25-4885-b606-43937e33f6e1", "crivo_dev_id": 316, "crivo_class_id": 12, "crivo_num_id": 12},
  {"result_id": "8def79a4-8c36-44b9-a6a8-4d2cdeeacfa3", "crivo_dev_id": 317, "crivo_class_id": 5, "crivo_num_id": null},
  {"result_id": "671cde7c-518b-4c5b-89ab-50ba2303b86c", "crivo_dev_id": 318, "crivo_class_id": 24, "crivo_num_id": 24},
  {"result_id": "fe6a1bea-dddb-4bfe-ae82-66382add4a69", "crivo_dev_id": 319, "crivo_class_id": null, "crivo_num_id": 9},
  {"result_id": "f86ce727-a2c7-49f9-874c-de31626afbca", "crivo_dev_id": 320, "crivo_class_id": null, "crivo_num_id": 10},
  {"result_id": "2025c865-b733-4f9c-b08f-109e4db57f44", "crivo_dev_id": 321, "crivo_class_id": 1, "crivo_num_id": null},
  {"result_id": "f5b319f5-7122-4b10-b2eb-0d1db4f28699", "crivo_dev_id": 322, "crivo_class_id": 7, "crivo_num_id": null},
  {"result_id": "235b35dc-3508-408f-bdde-d081b22e20a2", "crivo_dev_id": 323, "crivo_class_id": null, "crivo_num_id": null},
  {"result_id": "a70b99d1-179d-406c-91f1-dcab8c4a3398", "crivo_dev_id": 324, "crivo_class_id": 14, "crivo_num_id": 14},
  {"result_id": "6bfe5bc9-fbe0-4878-a86e-65cbdadc8f62", "crivo_dev_id": 325, "crivo_class_id": 15, "crivo_num_id": 15},
  {"result_id": "385733cb-60ba-40c0-a396-8291ab18c2d6", "crivo_dev_id": 326, "crivo_class_id": 9, "crivo_num_id": null},
  {"result_id": "80c455d6-362a-42a1-aa1a-f50abf8f33a5", "crivo_dev_id": 327, "crivo_class_id": 19, "crivo_num_id": 19}
]
